runnr/main.py
runnr/runnr_flags.py
runnr/runnr_parser.py
runnr/runnr_ver.py
runnr-0.3.0.dist-info/LICENSE
runnr-0.3.0.dist-info/METADATA
runnr-0.3.0.dist-info/WHEEL
runnr-0.3.0.dist-info/entry_points.txt
runnr-0.3.0.dist-info/top_level.txt
runnr-0.3.0.dist-info/RECORD
